{
  "db_name": "PostgreSQL",
  "query": "SELECT name, storage_path FROM files_metadata WHERE tenant_id = $1 AND is_deleted = true AND deleted_at < $2",
  "describe": {
    "columns": [
      {
        "ordinal": 0,
        "name": "name",
        "type_info": "Varchar"
      },
      {
        "ordinal": 1,
        "name": "storage_path",
        "type_info": "Text"
      }
    ],
    "parameters": {
      "Left": [
        "Uuid",
        "Timestamptz"
      ]
    },
    "nullable": [
      false,
      false
    ]
  },
  "hash": "8b353acac4267ff6d3606299bf2cf518fa6d540aeccc918ff4e85922186246c7"
}
